MANIFEST.in
README.html
README.in
README.rst
cblog-start
dev.cfg
prod.cfg
run
setup.py
CBlog.egg-info/PKG-INFO
CBlog.egg-info/SOURCES.txt
CBlog.egg-info/dependency_links.txt
CBlog.egg-info/entry_points.txt
CBlog.egg-info/not-zip-safe
CBlog.egg-info/paster_plugins.txt
CBlog.egg-info/requires.txt
CBlog.egg-info/sqlobject.txt
CBlog.egg-info/top_level.txt
cblog/__init__.py
cblog/cachecontrol.py
cblog/commands.py
cblog/fflash.py
cblog/model.py
cblog/release.py
cblog/config/__init__.py
cblog/config/app.cfg
cblog/config/cblog.cfg
cblog/config/log.cfg
cblog/controllers/__init__.py
cblog/controllers/feed.py
cblog/spamfilters/__init__.py
cblog/spamfilters/blacklist.py
cblog/spamfilters/content.py
cblog/spamfilters/content_blacklist.txt
cblog/static/rest.html
cblog/static/textile.html
cblog/static/css/articleform.css
cblog/static/css/cblog.css
cblog/static/css/commentform.css
cblog/static/css/fancyflash.css
cblog/static/css/html4css1.css
cblog/static/css/ie.css
cblog/static/css/login.css
cblog/static/css/rest.css
cblog/static/images/access-denied.gif
cblog/static/images/access-denied.png
cblog/static/images/biohazard.png
cblog/static/images/cancel.gif
cblog/static/images/cancel.png
cblog/static/images/error.gif
cblog/static/images/error.png
cblog/static/images/expando.gif
cblog/static/images/external-link-orange.gif
cblog/static/images/favicon.ico
cblog/static/images/feed.png
cblog/static/images/header_bg_orange.jpg
cblog/static/images/header_inner.png
cblog/static/images/info.gif
cblog/static/images/info.png
cblog/static/images/mail.gif
cblog/static/images/mail.png
cblog/static/images/ok.gif
cblog/static/images/ok.png
cblog/static/images/preview.png
cblog/static/images/preview_small.png
cblog/static/images/question.gif
cblog/static/images/question.png
cblog/static/images/refresh.gif
cblog/static/images/refresh.png
cblog/static/images/retracto.gif
cblog/static/images/save.gif
cblog/static/images/save.png
cblog/static/images/tg_under_the_hood.gif
cblog/static/images/tg_under_the_hood.png
cblog/static/images/tg_under_the_hood_sans_gear.gif
cblog/static/images/tg_under_the_hood_sans_gear.png
cblog/static/images/tip_topborder.gif
cblog/static/images/under_the_hood_blue.png
cblog/static/images/warning.gif
cblog/static/images/warning.png
