Metadata-Version: 1.0
Name: CBlog
Version: 0.1a
Summary: CBlog is a simple weblog application based on the TurboGears_ framework.
Home-page: http://chrisarndt.de/projects/cblog/
Author: Christopher Arndt
Author-email: chris@chrisarndt.de
License: MIT license
Download-URL: http://chrisarndt.de/projects/cblog/download/CBlog-0.1a-py2.4.egg
Keywords: turbogears.widgets,turbogears.app
Platform: UNKNOWN
Classifier: Development Status :: 3 - Alpha
Classifier: Environment :: Web Environment
Classifier: Framework :: TurboGears
Classifier: Framework :: TurboGears :: Applications
Classifier: Intended Audience :: Developers
Classifier: Intended Audience :: Education
Classifier: Intended Audience :: End Users/Desktop
Classifier: License :: OSI Approved :: MIT License
Classifier: Operating System :: OS Independent
Classifier: Programming Language :: Python
Classifier: Topic :: Internet :: WWW/HTTP :: Dynamic Content :: News/Diary
